seqstr
