Metadata-Version: 2.1
Name: seqstr
Version: 0.0.9
Summary: UNKNOWN
Home-page: https://github.com/jzhoulab/Seqstr/
Author: Chenlai Shi
Author-email: shichenlai@gmail.com
Maintainer: Chenlai Shi
Maintainer-email: shichenlai@gmail.com
License: MIT
Platform: UNKNOWN
License-File: LICENSE
